amla_sandbox/__init__.py
amla_sandbox/audit.py
amla_sandbox/auth.py
amla_sandbox/bash_tool.py
amla_sandbox/cli.py
amla_sandbox/codeact.py
amla_sandbox/langgraph.py
amla_sandbox/py.typed
amla_sandbox/sandbox.py
amla_sandbox/schema.py
amla_sandbox/_wasm/__init__.py
amla_sandbox/_wasm/amla_sandbox.wasm
amla_sandbox/capabilities/__init__.py
amla_sandbox/capabilities/constraints.py
amla_sandbox/capabilities/method.py
amla_sandbox/capabilities/patterns.py
amla_sandbox/runtime/__init__.py
amla_sandbox/runtime/wasm.py
amla_sandbox/tools/__init__.py
amla_sandbox/tools/conversion.py
amla_sandbox/tools/definition.py
amla_sandbox/tools/handlers.py
amla_sandbox/tools/ingest.py
amla_sandbox-0.1.6.dist-info/METADATA
amla_sandbox-0.1.6.dist-info/WHEEL
amla_sandbox-0.1.6.dist-info/entry_points.txt
amla_sandbox-0.1.6.dist-info/licenses/LICENSE
amla_sandbox-0.1.6.dist-info/licenses/NOTICES
amla_sandbox-0.1.6.dist-info/RECORD
