Metadata-Version: 2.4
Name: amla-sandbox
Version: 0.1.6
Summary: Capability-based sandboxed runtime for AI agents
Project-URL: Homepage, https://github.com/amlalabs/amla-sandbox
Project-URL: Repository, https://github.com/amlalabs/amla-sandbox
Project-URL: Issues, https://github.com/amlalabs/amla-sandbox/issues
Author-email: Amla Labs <hello@amla.dev>
License: MIT License
License-File: LICENSE
License-File: NOTICES
Keywords: agents,ai,capabilities,sandbox,security,wasm
Classifier: Development Status :: 3 - Alpha
Classifier: Intended Audience :: Developers
Classifier: License :: OSI Approved :: MIT License
Classifier: Programming Language :: Python :: 3
Classifier: Programming Language :: Python :: 3.11
Classifier: Programming Language :: Python :: 3.12
Classifier: Programming Language :: Python :: 3.13
Classifier: Topic :: Security
Classifier: Topic :: Software Development :: Libraries :: Python Modules
Requires-Python: >=3.11
Requires-Dist: cryptography>=43.0.0
Requires-Dist: wasmtime>=29.0.0
Provides-Extra: all
Requires-Dist: langchain-anthropic>=0.3.0; extra == 'all'
Requires-Dist: langchain-core>=0.3.0; extra == 'all'
Requires-Dist: langchain-openai>=0.3.0; extra == 'all'
Requires-Dist: langchain>=0.3.0; extra == 'all'
Requires-Dist: langgraph-codeact>=0.0.1; extra == 'all'
Requires-Dist: langgraph>=0.2.0; extra == 'all'
Requires-Dist: python-dotenv>=1.0.0; extra == 'all'
Provides-Extra: codeact
Requires-Dist: langchain-anthropic>=0.3.0; extra == 'codeact'
Requires-Dist: langchain>=0.3.0; extra == 'codeact'
Requires-Dist: langgraph-codeact>=0.0.1; extra == 'codeact'
Provides-Extra: dev
Requires-Dist: pyright>=1.1.390; extra == 'dev'
Requires-Dist: pytest-asyncio>=0.24.0; extra == 'dev'
Requires-Dist: pytest>=8.0.0; extra == 'dev'
Requires-Dist: ruff>=0.8.0; extra == 'dev'
Provides-Extra: langgraph
Requires-Dist: langchain-anthropic>=0.3.0; extra == 'langgraph'
Requires-Dist: langchain-core>=0.3.0; extra == 'langgraph'
Requires-Dist: langchain-openai>=0.3.0; extra == 'langgraph'
Requires-Dist: langchain>=0.3.0; extra == 'langgraph'
Requires-Dist: langgraph>=0.2.0; extra == 'langgraph'
Requires-Dist: python-dotenv>=1.0.0; extra == 'langgraph'
